dracula/__init__.py
dracula_metadata_updater-1.0.dist-info/METADATA
dracula_metadata_updater-1.0.dist-info/WHEEL
dracula_metadata_updater-1.0.dist-info/entry_points.txt
dracula_metadata_updater-1.0.dist-info/top_level.txt
dracula_metadata_updater-1.0.dist-info/RECORD
