Metadata-Version: 2.1
Name: dracula-metadata-updater
Version: 1.0
Summary: A script to update metadata of 뮤지컬 드라큘라(Dracula) OST 〈10TH ANNIVERSARY CAST RECORDING〉
Author: Hankan1918
Classifier: Programming Language :: Python :: 3
Classifier: License :: OSI Approved :: MIT License
Classifier: Operating System :: OS Independent
Requires-Python: >=3.6
Requires-Dist: mutagen
